_JNJ/Babel.py
_JNJ/Environment.py
_JNJ/GTW.py
_JNJ/LICENSE
_JNJ/Media_Defaults.py
_JNJ/Onion.py
_JNJ/README.rst
_JNJ/SRM.py
_JNJ/Templateer.py
_JNJ/VERSION.py
_JNJ/__init__.py
_JNJ/babel.cfg
_JNJ/setup.cfg
_JNJ/setup.py
_JNJ/-I18N/de.po
_JNJ/-I18N/en.po
_JNJ/-I18N/pt.po
_JNJ/-I18N/template.pot
_JNJ/email/change_email_info.jnj
_JNJ/email/change_password_info.jnj
_JNJ/email/email.jnj
_JNJ/email/error.jnj
_JNJ/email/regatta_register.jnj
_JNJ/email/reset_password.jnj
_JNJ/email/verify_new_email.jnj
_JNJ/html/5.jnj
_JNJ/html/_input.jnj
_JNJ/html/_input.jnj.media
_JNJ/html/action_button.m.jnj
_JNJ/html/auth.m.jnj
_JNJ/html/auth.m.jnj.media
_JNJ/html/auth.media
_JNJ/html/autocomplete.media
_JNJ/html/babel.cfg
_JNJ/html/base.jnj
_JNJ/html/base.jnj.media
_JNJ/html/base.m.jnj
_JNJ/html/base.media
_JNJ/html/base_classes.media
_JNJ/html/base_rest.media
_JNJ/html/cal_day.jnj
_JNJ/html/calendar.jnj
_JNJ/html/calendar.jnj.media
_JNJ/html/change_email.jnj
_JNJ/html/change_email.jnj.media
_JNJ/html/change_password.jnj
_JNJ/html/change_password.jnj.media
_JNJ/html/clip_aggregator.jnj
_JNJ/html/clip_aggregator.jnj.media
_JNJ/html/cmd_button.media
_JNJ/html/cmd_menu.media
_JNJ/html/console.jnj
_JNJ/html/console.jnj.media
_JNJ/html/css_arrows.media
_JNJ/html/css_menu_icon.media
_JNJ/html/e_type.m.jnj
_JNJ/html/e_type.m.jnj.media
_JNJ/html/e_type_admin.jnj
_JNJ/html/e_type_admin.jnj.media
_JNJ/html/e_type_admin.media
_JNJ/html/e_type_display.jnj
_JNJ/html/e_type_display.jnj.media
_JNJ/html/e_type_doc.jnj
_JNJ/html/e_type_doc.m.jnj
_JNJ/html/e_type_doc.m.jnj.media
_JNJ/html/e_type_doc_bare.jnj
_JNJ/html/e_type_mf3.jnj
_JNJ/html/e_type_q.m.jnj
_JNJ/html/e_type_selector.m.jnj
_JNJ/html/elfinder.jnj
_JNJ/html/elfinder.jnj.media
_JNJ/html/empty_dir.jnj
_JNJ/html/empty_dir.jnj.media
_JNJ/html/error.jnj
_JNJ/html/error_400.jnj
_JNJ/html/error_401.jnj
_JNJ/html/error_401.jnj.media
_JNJ/html/error_403.jnj
_JNJ/html/error_404.jnj
_JNJ/html/error_405.jnj
_JNJ/html/error_408.jnj
JNJ-3.9.dist-info/LICENSE
JNJ-3.9.dist-info/METADATA
JNJ-3.9.dist-info/WHEEL
JNJ-3.9.dist-info/top_level.txt
JNJ-3.9.dist-info/RECORD
