Metadata-Version: 2.1
Name: JNJ
Version: 3.9
Summary: Package providing a Jinja2-based template framework.
Home-page: https://codeberg.org/tanzer/tapyr
Author: Christian Tanzer
Author-email: tanzer@swing.co.at
License: BSD License
Platform: Any
Classifier: Development Status :: 5 - Production/Stable
Classifier: License :: OSI Approved :: BSD License
Classifier: Operating System :: OS Independent
Classifier: Programming Language :: Python
Classifier: Intended Audience :: Developers
Classifier: Topic :: Internet :: WWW/HTTP :: Dynamic Content
Classifier: Topic :: Software Development :: Libraries :: Python Modules
Classifier: Topic :: Text Processing :: Markup :: HTML
Requires-Python: >=3.9
License-File: LICENSE
Requires-Dist: TFL (>=3)
Requires-Dist: CHJ (>=3)
Requires-Dist: jinja2
